fguess.py
fguess-0.0.1.dist-info/METADATA
fguess-0.0.1.dist-info/WHEEL
fguess-0.0.1.dist-info/entry_points.txt
fguess-0.0.1.dist-info/licenses/LICENSE.txt
fguess-0.0.1.dist-info/RECORD
