Metadata-Version: 2.4
Name: fguess
Version: 0.0.1
Summary: f-string format spec guesser
Project-URL: Documentation, https://github.com/treyhunner/fguess#readme
Project-URL: Issues, https://github.com/treyhunner/fguess/issues
Project-URL: Source, https://github.com/treyhunner/fguess
Author: Trey Hunner
License-Expression: MIT
License-File: LICENSE.txt
Classifier: Development Status :: 2 - Pre-Alpha
Classifier: Programming Language :: Python
Classifier: Programming Language :: Python :: 3.9
Classifier: Programming Language :: Python :: 3.10
Classifier: Programming Language :: Python :: 3.11
Classifier: Programming Language :: Python :: 3.12
Classifier: Programming Language :: Python :: 3.13
Classifier: Programming Language :: Python :: 3.14
Classifier: Programming Language :: Python :: Implementation :: CPython
Classifier: Programming Language :: Python :: Implementation :: PyPy
Requires-Python: >=3.9
Requires-Dist: strptime-cli
